fiberkit/AISC.csv
fiberkit/__init__.py
fiberkit/nodefiber.py
fiberkit/patchfiber.py
fiberkit/plotter.py
fiberkit/section.py
fiberkit/sectionbuilder.py
fiberkit-2.0.0.dist-info/METADATA
fiberkit-2.0.0.dist-info/WHEEL
fiberkit-2.0.0.dist-info/licenses/LICENSE
fiberkit-2.0.0.dist-info/RECORD
