Metadata-Version: 2.4
Name: fiberkit
Version: 2.0.0
Summary: Fiber Kit - moment curvature analysis for reinforced concrete, steel, wood, etc.
Project-URL: Homepage, https://github.com/wcfrobert/fkit
Project-URL: Bug Tracker, https://github.com/wcfrobert/fkit/issues
Author-email: wcfrobert <temprobertdev@gmail.com>
License-File: LICENSE
Keywords: PM Interaction,concrete,fiber,moment curvature,reinforced concrete,section analysis,steel,structural engineering,timber
Classifier: License :: OSI Approved :: MIT License
Classifier: Operating System :: OS Independent
Classifier: Programming Language :: Python :: 3
Requires-Python: >=3.7
Requires-Dist: matplotlib>=3.7
Requires-Dist: numpy>=2.0
Requires-Dist: pandas>=2.0
Requires-Dist: plotly>=6.0
